vvrest/__init__.py
vvrest/constants.py
vvrest/token.py
vvrest/utilities.py
vvrest/vault.py
vvrest/services/__init__.py
vvrest/services/auth_service.py
vvrest/services/document_service.py
vvrest/services/email_service.py
vvrest/services/file_service.py
vvrest/services/folder_service.py
vvrest/services/form_service.py
vvrest/services/group_service.py
vvrest/services/index_field_service.py
vvrest/services/site_service.py
vvrest/services/user_service.py
vvrest-1.8.0.dist-info/LICENSE
vvrest-1.8.0.dist-info/METADATA
vvrest-1.8.0.dist-info/WHEEL
vvrest-1.8.0.dist-info/top_level.txt
vvrest-1.8.0.dist-info/RECORD
