Metadata-Version: 2.1
Name: vvrest
Version: 1.8.0
Summary: A Python REST client library for accessing VisualVault.
Home-page: https://github.com/VisualVault/vvrest
Author: Jared Runyon
Author-email: jared.runyon@visualvault.com
Maintainer: Jared Runyon
Maintainer-email: jared.runyon@visualvault.com
License: UNKNOWN
Platform: UNKNOWN
Classifier: Intended Audience :: Developers
Classifier: Programming Language :: Python
Classifier: Programming Language :: Python :: 3
Classifier: Programming Language :: Python :: 3 :: Only
Classifier: Programming Language :: Python :: 3.5
Classifier: Programming Language :: Python :: 3.6
Classifier: Programming Language :: Python :: 3.7
Classifier: Programming Language :: Python :: 3.8
Classifier: Programming Language :: Python :: 3.9
Classifier: License :: OSI Approved :: MIT License
Classifier: Operating System :: OS Independent
Classifier: Topic :: Internet :: WWW/HTTP
Classifier: Topic :: Software Development :: Libraries :: Python Modules
License-File: LICENSE
Requires-Dist: requests
